ourkvm/__init__.py
ourkvm/__main__.py
ourkvm/api/__init__.py
ourkvm/api/app.py
ourkvm/api/capabilities.py
ourkvm/api/monitoring.py
ourkvm/api/networking.py
ourkvm/api/qemu.py
ourkvm/api/resources.py
ourkvm/api/security.py
ourkvm/cluster/__init__.py
ourkvm/cluster/clusterserver.py
ourkvm/lib/__init__.py
ourkvm/lib/helpers/__init__.py
ourkvm/lib/helpers/dupedict.py
ourkvm/lib/helpers/exceptions.py
ourkvm/lib/helpers/logger.py
ourkvm/lib/helpers/paths.py
ourkvm/lib/helpers/syscalls.py
ourkvm/lib/networking/__init__.py
ourkvm/lib/networking/interfaces.py
ourkvm/lib/networking/net.py
ourkvm/lib/networking/structs.py
ourkvm/lib/qemu/__init__.py
ourkvm/lib/qemu/environment.py
ourkvm/lib/qemu/qemu.py
ourkvm/lib/qemu/resources.py
ourkvm/lib/qemu/snapshots.py
ourkvm/storage/__init__.py
python_ourkvm-0.0.24.dist-info/entry_points.txt
python_ourkvm-0.0.24.dist-info/LICENSE
python_ourkvm-0.0.24.dist-info/WHEEL
python_ourkvm-0.0.24.dist-info/METADATA
python_ourkvm-0.0.24.dist-info/RECORD
